Envella/Envella.py
Envella/__init__.py
Envella/exceptions.py
Envella/utils.py
envella-1.0.0.dist-info/licenses/LICENSE
tests/__init__.py
tests/test_secure_dotenv.py
envella-1.0.0.dist-info/METADATA
envella-1.0.0.dist-info/WHEEL
envella-1.0.0.dist-info/top_level.txt
envella-1.0.0.dist-info/RECORD
