Metadata-Version: 2.4
Name: Envella
Version: 1.0.0
Summary: A comprehensive, secure and advanced library for managing .env files
Home-page: https://github.com/mohammadamin382/Envella_library.git
Author: Mohammad Hosseini
Author-email: Mohammad Hosseini <mohammad.hosseini@example.com>
License: GPL-3.0
Project-URL: Repository, https://github.com/mohammadamin382/Envella_library.git
Project-URL: Bug Tracker, https://github.com/mohammadamin382/Envella_library/issues
Project-URL: Documentation, https://github.com/mohammadamin382/Envella_library
Classifier: Development Status :: 5 - Production/Stable
Classifier: Intended Audience :: Developers
Classifier: Topic :: Software Development :: Libraries :: Python Modules
Classifier: License :: OSI Approved :: GNU General Public License v3 (GPLv3)
Classifier: Programming Language :: Python :: 3
Classifier: Programming Language :: Python :: 3.7
Classifier: Programming Language :: Python :: 3.8
Classifier: Programming Language :: Python :: 3.9
Classifier: Programming Language :: Python :: 3.10
Classifier: Programming Language :: Python :: 3.11
Classifier: Operating System :: OS Independent
Requires-Python: >=3.7
License-File: LICENSE
Requires-Dist: cryptography>=44.0.2
Provides-Extra: dev
Requires-Dist: pytest>=8.3.5; extra == "dev"
Requires-Dist: black>=22.0.0; extra == "dev"
Requires-Dist: flake8>=4.0.0; extra == "dev"
Requires-Dist: mypy>=0.900; extra == "dev"
Requires-Dist: isort>=5.0.0; extra == "dev"
Provides-Extra: test
Requires-Dist: pytest>=8.3.5; extra == "test"
Requires-Dist: pytest-cov>=3.0.0; extra == "test"
Provides-Extra: advanced
Requires-Dist: argon2-cffi>=21.0.0; extra == "advanced"
Requires-Dist: zxcvbn>=4.4.28; extra == "advanced"
Requires-Dist: pyotp>=2.8.0; extra == "advanced"
Dynamic: author
Dynamic: home-page
Dynamic: license-file
Dynamic: requires-python
